setup.py
Calculadora_Clases/__init__.py
Calculadora_Clases - copia/CalculatorDivision.py
Calculadora_Clases - copia/CalculatorMultiplicar.py
Calculadora_Clases - copia/CalculatorResta.py
Calculadora_Clases - copia/CalculatorSuma.py
Calculadora_Clases - copia/MainCalculatorConsole.py
Calculadora_Clases - copia/__init__.py
Calculadora_Clases - copia/prueba.py
pruebix.egg-info/PKG-INFO
pruebix.egg-info/SOURCES.txt
pruebix.egg-info/dependency_links.txt
pruebix.egg-info/top_level.txt