Metadata-Version: 1.1
Name: pruebix
Version: 0.0.1
Summary: Operaciones de 2 digitos
Home-page: UNKNOWN
Author: Wilbert Sanchez
Author-email: wilbertenriquechable522@gmail.com
License: MIT
Keywords: calculator
Platform: UNKNOWN
Classifier: Development Status :: 5 - Production/Stable
Classifier: Intended Audience :: Education
Classifier: Operating System :: Microsoft :: Windows :: Windows 10
Classifier: License :: OSI Approved :: MIT License
Classifier: Programming Language :: Python :: 3
